{
    "inherits": "dremel_base",
    "name": "Dremel PLA Matte @3D40",
    "from": "system",
    "type": "filament",
    "version": "2.0.0.2",
    "instantiation": "true",
	"compatible_printers": [
		"Dremel 3D40 0.4 nozzle"
	],
    "activate_air_filtration": [
        "1"
    ],
    "additional_cooling_fan_speed": [
        "0"
    ],
    "complete_print_exhaust_fan_speed": [
        "0"
    ],
    "default_filament_colour": [
        "#964B00"
    ],
    "during_print_exhaust_fan_speed": [
        "100"
    ],
    "fan_min_speed": [
        "100"
    ],
    "filament_cost": [
        "35.99"
    ],
    "filament_flow_ratio": [
        "1.024"
    ],
    "filament_max_volumetric_speed": [
        "14.75"
    ],
    "filament_settings_id": [
        "Dremel PLA Matte"
    ],
    "filament_vendor": [
        "Dremel"
    ],
    "full_fan_speed_layer": [
        "2"
    ],
    "overhang_fan_threshold": [
        "95%"
    ],
    "pressure_advance": [
        "0.014"
    ],
    "slow_down_layer_time": [
        "0"
    ],
    "temperature_vitrification": [
        "65"
    ],
    "nozzle_temperature": [
        "220"
    ],
    "nozzle_temperature_initial_layer": [
        "220"
    ],
    "nozzle_temperature_range_high": [
        "240"
    ],
    "nozzle_temperature_range_low": [
        "210"
    ],
    "cool_plate_temp": [
        "45"
    ],
    "cool_plate_temp_initial_layer": [
        "45"
    ],
    "textured_cool_plate_temp": [
        "45"
    ],
    "textured_cool_plate_temp_initial_layer": [
        "45"
    ],
    "hot_plate_temp": [
        "45"
    ],
    "hot_plate_temp_initial_layer": [
        "45"
    ],
	"smooth_pei_plate_temp":[
		"45"
	],
    "smooth_pei_plate_temp_initial_layer":[
		"45"
	],
    "textured_plate_temp": [
        "45"
    ],
    "textured_plate_temp_initial_layer": [
        "45"
    ]
}
